{"lang":"PHP","lines":243,"size":9149,"markdown":null,"scores":{"security":10,"performance":10,"architecture":10,"quality":9,"documentation":5},"issues":{"security":[],"performance":[],"architecture":[],"quality":[{"severity":"moderate","message":"Ligne dupliquee 5 fois (lignes 34, 50, 83, 117, 149) : if (! $this->checkDemo()) {...","line":34}],"documentation":[{"severity":"info","message":"Methode index() sans bloc PHPDoc","line":32},{"severity":"info","message":"Methode uploadPhotos() sans bloc PHPDoc","line":48},{"severity":"info","message":"Methode uploadGed() sans bloc PHPDoc","line":81},{"severity":"info","message":"Methode deleteFile() sans bloc PHPDoc","line":115},{"severity":"info","message":"Methode reset() sans bloc PHPDoc","line":147}]},"ai":null}