{"lang":"PHP","lines":52,"size":1615,"markdown":null,"scores":{"security":10,"performance":10,"architecture":10,"quality":10,"documentation":0},"issues":{"security":[],"performance":[],"architecture":[],"quality":[],"documentation":[{"severity":"info","message":"Methode test_owner_peut_editer() sans bloc PHPDoc","line":13},{"severity":"info","message":"Methode test_member_peut_editer() sans bloc PHPDoc","line":18},{"severity":"info","message":"Methode test_viewer_ne_peut_pas_editer() sans bloc PHPDoc","line":23},{"severity":"info","message":"Methode test_seul_owner_peut_gerer() sans bloc PHPDoc","line":28},{"severity":"info","message":"Methode test_labels_en_francais() sans bloc PHPDoc","line":35},{"severity":"info","message":"Methode test_values_retourne_toutes_les_valeurs() sans bloc PHPDoc","line":42}]},"ai":null}