{"lang":"PHP","lines":94,"size":2901,"markdown":null,"scores":{"security":10,"performance":9.5,"architecture":10,"quality":8,"documentation":1},"issues":{"security":[],"performance":[{"severity":"info","message":"Acces frequent a des relations sans eager-loading detecte (->with()) : verifier le risque N+1","line":1,"excerpt":""}],"architecture":[],"quality":[{"severity":"moderate","message":"Ligne dupliquee 4 fois (lignes 30, 36, 42, 91) : return $this->permissions->canAdmin($user, $folder);...","line":30},{"severity":"moderate","message":"Ligne dupliquee 3 fois (lignes 56, 68, 80) : $folder = $document->folder;...","line":56}],"documentation":[{"severity":"info","message":"Methode view() sans bloc PHPDoc","line":16},{"severity":"info","message":"Methode upload() sans bloc PHPDoc","line":22},{"severity":"info","message":"Methode update() sans bloc PHPDoc","line":28},{"severity":"info","message":"Methode delete() sans bloc PHPDoc","line":34},{"severity":"info","message":"Methode managePermissions() sans bloc PHPDoc","line":40},{"severity":"info","message":"Methode download() sans bloc PHPDoc","line":46},{"severity":"info","message":"Methode viewDocument() sans bloc PHPDoc","line":54},{"severity":"info","message":"Methode downloadDocument() sans bloc PHPDoc","line":66},{"severity":"info","message":"Methode manageDocument() sans bloc PHPDoc","line":78}]},"ai":null}