{"lang":"PHP","lines":197,"size":6849,"markdown":null,"scores":{"security":10,"performance":10,"architecture":10,"quality":5,"documentation":1.3},"issues":{"security":[],"performance":[],"architecture":[],"quality":[{"severity":"moderate","message":"Ligne dupliquee 7 fois (lignes 58, 66, 74, 82, 90) : $service = new WatermarkService;...","line":58},{"severity":"moderate","message":"Ligne dupliquee 5 fois (lignes 65, 73, 81, 89, 132) : $settings = TenantSettings::factory()->make(['wm_enabled' =>...","line":65},{"severity":"moderate","message":"Ligne dupliquee 3 fois (lignes 147, 171, 188) : $this->actingAs($this->admin, 'tenant')...","line":147},{"severity":"moderate","message":"Ligne dupliquee 3 fois (lignes 148, 172, 189) : ->put(route('admin.settings.media.update'), [...","line":148},{"severity":"moderate","message":"Ligne dupliquee 3 fois (lignes 149, 173, 190) : 'media_default_cols' => 3,...","line":149}],"documentation":[{"severity":"info","message":"Methode test_should_apply_retourne_false_si_wm_disabled() sans bloc PHPDoc","line":55},{"severity":"info","message":"Methode test_should_apply_retourne_true_pour_jpeg_si_wm_enabled() sans bloc PHPDoc","line":63},{"severity":"info","message":"Methode test_should_apply_retourne_true_pour_png_si_wm_enabled() sans bloc PHPDoc","line":71},{"severity":"info","message":"Methode test_should_apply_retourne_false_pour_video() sans bloc PHPDoc","line":79},{"severity":"info","message":"Methode test_should_apply_retourne_false_pour_pdf() sans bloc PHPDoc","line":87},{"severity":"info","message":"Methode test_apply_retourne_jpeg_watermarked() sans bloc PHPDoc","line":97},{"severity":"info","message":"Methode test_admin_peut_activer_le_watermark() sans bloc PHPDoc","line":143}]},"ai":null}